modulesync/__init__.py
modulesync/__main__.py
modulesync/modulesync.py
modulesync-0.0.1.dist-info/LICENSE
modulesync-0.0.1.dist-info/METADATA
modulesync-0.0.1.dist-info/WHEEL
modulesync-0.0.1.dist-info/entry_points.txt
modulesync-0.0.1.dist-info/top_level.txt
modulesync-0.0.1.dist-info/RECORD
